library_nsxt/__init__.py
library_nsxt/create_group_cluster.py
library_nsxt/exceptions/__init__.py
library_nsxt/exceptions/nsxt_errors.py
library_nsxt/models/__init__.py
library_nsxt/models/nsxt_model.py
library_nsxt/models/generic/__init__.py
library_nsxt/models/generic/nsx_group.py
library_nsxt/models/generic/nsx_rules_and_sections.py
library_nsxt/models/load_balancing/__init__.py
library_nsxt/models/load_balancing/pool.py
library_nsxt/models/load_balancing/vserver.py
library_nsxt/models/security/__init__.py
library_nsxt/models/security/group.py
library_nsxt/models/security/ip_set.py
library_nsxt/models/security/nsxt_security_model.py
library_nsxt/models/security/policy.py
library_nsxt/models/security/rule.py
library_nsxt/models/security/service.py
library_nsxt/models/security/vmachine.py
library_nsxt/services/__init__.py
library_nsxt/services/create_group_cluster.py
library_nsxt/services/nsxt_api_client.py
library_nsxt/services/nsxt_api_parser.py
library_nsxt/services/nsxt_api_session.py
library_nsxt/services/nsxt_policy_api_client.py
library_nsxt-1.0.8.post19.dist-info/LICENSE.md
library_nsxt-1.0.8.post19.dist-info/METADATA
library_nsxt-1.0.8.post19.dist-info/WHEEL
library_nsxt-1.0.8.post19.dist-info/entry_points.txt
library_nsxt-1.0.8.post19.dist-info/top_level.txt
library_nsxt-1.0.8.post19.dist-info/RECORD
