Metadata-Version: 2.1
Name: library-nsxt
Version: 1.0.8.post19
Summary: Implements methods and models for interacting with a NSXT cluster.
Home-page: UNKNOWN
Author: The_Crazy_Sys_Admin
License: UNKNOWN
Platform: UNKNOWN
Requires-Python: >=3.6.8, <4
Requires-Dist: requests
Requires-Dist: core-commons (<2,>=1.0.3)
